{"digest":"2522d48a8802498cc08076ea0fbbe705ada07d33","css":"/**\n * Colors\n */\n/**\n * Borders\n */\n.release-bar {\n  order: -1;\n}\n.release-bar-inner {\n  height: 25px;\n  display: block;\n  padding-left: 10px;\n  padding-top: 2px;\n  color: #87939a;\n  background-color: #00ac6f;\n  border-bottom: 1px solid #00794e;\n}\n.release-bar-inner:hover {\n  background-color: #00794e;\n  border-bottom: 1px solid #00603e;\n  text-decoration: none;\n  color: white;\n}\n.release-bar-inner i {\n  margin-right: 8px;\n}\n","imports":[{"path":"static/variables/ui-variables.less","digest":"391921cec1ce13fe8cd456d1775e958a2acade6f"},{"path":"internal_packages/ui-taiga/styles/ui-variables.less","digest":"437a528543b6e9831134ea19c9e7e4a78f9a27c4"},{"path":"internal_packages/ui-taiga/styles/variables.less","digest":"ecf0bd203a77cefbcab0029120c73a9c607696b6"}],"version":1}